mlsriracha/__init__.py
mlsriracha/deploy.py
mlsriracha/process.py
mlsriracha/train.py
mlsriracha/interfaces/__init__.py
mlsriracha/interfaces/deploy.py
mlsriracha/interfaces/metadata.py
mlsriracha/interfaces/process.py
mlsriracha/interfaces/train.py
mlsriracha/plugins/__init__.py
mlsriracha/plugins/awssagemaker/__init__.py
mlsriracha/plugins/awssagemaker/deploy.py
mlsriracha/plugins/awssagemaker/process.py
mlsriracha/plugins/awssagemaker/train.py
mlsriracha/plugins/azureml/__init__.py
mlsriracha/plugins/azureml/deploy.py
mlsriracha/plugins/azureml/train.py
mlsriracha/plugins/gcpvertex/__init__.py
mlsriracha/plugins/gcpvertex/deploy.py
mlsriracha/plugins/gcpvertex/train.py
mlsriracha/plugins/kubernetes/__init__.py
mlsriracha/plugins/kubernetes/deploy.py
mlsriracha/plugins/kubernetes/process.py
mlsriracha/plugins/kubernetes/train.py
mlsriracha/plugins/kubernetes/common/__init__.py
mlsriracha/plugins/kubernetes/common/helper.py
mlsriracha/plugins/mlflow/__init__.py
mlsriracha/plugins/mlflow/metadata.py
tests/__init__.py
tests/test_training_adapter.py
mlsriracha-0.0.4.dist-info/LICENSE
mlsriracha-0.0.4.dist-info/METADATA
mlsriracha-0.0.4.dist-info/WHEEL
mlsriracha-0.0.4.dist-info/top_level.txt
mlsriracha-0.0.4.dist-info/RECORD
